.mailmap
AUTHORS
ChangeLog
LICENSE
MANIFEST.in
README.rst
openstack-common.conf
requirements.txt
setup.cfg
setup.py
test-requirements.txt
tox.ini
savanna_dashboard.egg-info/PKG-INFO
savanna_dashboard.egg-info/SOURCES.txt
savanna_dashboard.egg-info/dependency_links.txt
savanna_dashboard.egg-info/not-zip-safe
savanna_dashboard.egg-info/requires.txt
savanna_dashboard.egg-info/top_level.txt
savannadashboard/__init__.py
savannadashboard/dashboard.py
savannadashboard/version.py
savannadashboard/api/__init__.py
savannadashboard/api/client.py
savannadashboard/api/helpers.py
savannadashboard/cluster_templates/__init__.py
savannadashboard/cluster_templates/forms.py
savannadashboard/cluster_templates/panel.py
savannadashboard/cluster_templates/tables.py
savannadashboard/cluster_templates/tabs.py
savannadashboard/cluster_templates/urls.py
savannadashboard/cluster_templates/views.py
savannadashboard/cluster_templates/workflows/__init__.py
savannadashboard/cluster_templates/workflows/copy.py
savannadashboard/cluster_templates/workflows/create.py
savannadashboard/clusters/__init__.py
savannadashboard/clusters/panel.py
savannadashboard/clusters/tables.py
savannadashboard/clusters/tabs.py
savannadashboard/clusters/urls.py
savannadashboard/clusters/views.py
savannadashboard/clusters/workflows/__init__.py
savannadashboard/clusters/workflows/create.py
savannadashboard/clusters/workflows/scale.py
savannadashboard/data_sources/__init__.py
savannadashboard/data_sources/panel.py
savannadashboard/data_sources/tables.py
savannadashboard/data_sources/tabs.py
savannadashboard/data_sources/urls.py
savannadashboard/data_sources/views.py
savannadashboard/data_sources/workflows/__init__.py
savannadashboard/data_sources/workflows/create.py
savannadashboard/image_registry/__init__.py
savannadashboard/image_registry/forms.py
savannadashboard/image_registry/panel.py
savannadashboard/image_registry/tables.py
savannadashboard/image_registry/urls.py
savannadashboard/image_registry/views.py
savannadashboard/job_binaries/__init__.py
savannadashboard/job_binaries/forms.py
savannadashboard/job_binaries/panel.py
savannadashboard/job_binaries/tables.py
savannadashboard/job_binaries/tabs.py
savannadashboard/job_binaries/urls.py
